sshse/__init__.py
sshse/__main__.py
sshse/adapters/__init__.py
sshse/cli/__init__.py
sshse/cli/_shared.py
sshse/cli/app.py
sshse/cli/config.py
sshse/cli/creds.py
sshse/cli/history_browser.py
sshse/cli/ssh_launcher.py
sshse/config/__init__.py
sshse/core/__init__.py
sshse/core/credentials.py
sshse/core/history.py
sshse/core/interfaces.py
sshse/plugins/__init__.py
sshse-0.2.0.dist-info/licenses/LICENSE
sshse-0.2.0.dist-info/METADATA
sshse-0.2.0.dist-info/WHEEL
sshse-0.2.0.dist-info/entry_points.txt
sshse-0.2.0.dist-info/top_level.txt
sshse-0.2.0.dist-info/RECORD
