Metadata-Version: 2.4
Name: sshse
Version: 0.2.0
Summary: SSH Session Manager (sshse) application
Author: Ido Segev
License-Expression: MIT
Requires-Python: >=3.11
License-File: LICENSE
Requires-Dist: argon2-cffi>=23.1
Requires-Dist: cryptography>=42.0.0
Requires-Dist: platformdirs>=4.2
Requires-Dist: typer>=0.12
Provides-Extra: dev
Requires-Dist: black>=24.0; extra == "dev"
Requires-Dist: ruff>=0.5.0; extra == "dev"
Requires-Dist: mypy>=1.8; extra == "dev"
Requires-Dist: pytest>=7.4; extra == "dev"
Requires-Dist: pytest-cov>=4.1; extra == "dev"
Requires-Dist: coverage[toml]>=7.3; extra == "dev"
Requires-Dist: bandit>=1.7; extra == "dev"
Requires-Dist: pre-commit>=3.6; extra == "dev"
Dynamic: license-file
